django_mjml-1.5.dist-info/licenses/LICENSE
mjml/__init__.py
mjml/apps.py
mjml/settings.py
mjml/tools.py
mjml/templatetags/__init__.py
mjml/templatetags/mjml.py
django_mjml-1.5.dist-info/METADATA
django_mjml-1.5.dist-info/WHEEL
django_mjml-1.5.dist-info/top_level.txt
django_mjml-1.5.dist-info/RECORD
